{
  "employees": [
    {
      "id": 1,
      "first_name": "Sebastian",
      "last_name": "Eschweiler",
      "email": "sebastian@codingthesmartway.com",
      "title": "Runner",
      "hiredDate": "1/10-2018"
    },
    {
      "id": 2,
      "first_name": "Steve",
      "last_name": "Palmer",
      "email": "steve@codingthesmartway.com",
      "title": "Developer",
      "hiredDate": "1/4-2014"
    },
    {
      "id": 3,
      "first_name": "Ann",
      "last_name": "Smith",
      "email": "ann@codingthesmartway.com",
      "title": "Senior Developer",
      "hiredDate": "1/3-2008"
    }
  ]
}
